LICENSE
MANIFEST.in
README.md
setup.py
dfer_tools_python.egg-info/PKG-INFO
dfer_tools_python.egg-info/SOURCES.txt
dfer_tools_python.egg-info/dependency_links.txt
dfer_tools_python.egg-info/top_level.txt
src/__init__.py
src/__version__.py
src/core.py
src/common/__init__.py
src/common/test.py